{
  "hbo-max": { "total_movies": 1103, "scraped_movies": 1103 },
  "apple-tv-plus": { "total_movies": 57, "scraped_movies": 57 },
  "netflix-basic-with-ads": { "total_movies": 5188, "scraped_movies": 4566 },
  "netflix": { "total_movies": 5324, "scraped_movies": 4665 },
  "disney": { "total_movies": 1702, "scraped_movies": 1702 },
  "amazon-prime-video": { "total_movies": 4174, "scraped_movies": 4056 },
  "filmin": { "total_movies": 9258, "scraped_movies": 6735 },
  "movistar-plus": { "total_movies": 1695, "scraped_movies": 1697 },
  "filmin-plus": { "total_movies": 365, "scraped_movies": 366 },
  "skyshowtime": { "total_movies": 707, "scraped_movies": 707 },
  "atres-player": { "total_movies": 212, "scraped_movies": 212 }
}
